triplethreading/__init__.py
triplethreading/_core.abi3.so
triplethreading/_core.pyi
triplethreading/py.typed
triplethreading/differential/__init__.py
triplethreading/differential/discrete.py
triplethreading/distributions/__init__.py
triplethreading/distributions/cvdistributions.py
triplethreading/matrix/__init__.py
triplethreading/matrix/elementary.py
triplethreading/model/Hydropower.csv
triplethreading/model/Hydropower_Scatter.pdf
triplethreading/model/__init__.py
triplethreading/model/regression.py
triplethreading-0.5.0.dist-info/METADATA
triplethreading-0.5.0.dist-info/WHEEL
triplethreading-0.5.0.dist-info/RECORD
