Metadata-Version: 2.4
Name: triplethreading
Version: 0.5.0
Requires-Dist: auditwheel>=6.4.2
Requires-Dist: matplotlib>=3.10.6
Requires-Dist: numpy>=2.3.2
Requires-Dist: patchelf>=0.17.2.4
Requires-Dist: polars>=1.34.0
Requires-Dist: scipy>=1.16.2
Requires-Dist: torch>=2.8.0
Requires-Dist: twine>=6.1.0
Summary: Add your description here
Author-email: triplethreading <triplethreading@gmail.com>
Requires-Python: >=3.11
